aigie/__init__.py
aigie/agent.py
aigie/alerting.py
aigie/analytics.py
aigie/annotations.py
aigie/backend_client.py
aigie/batch_evaluation.py
aigie/buffer.py
aigie/callback.py
aigie/checkpoint.py
aigie/client.py
aigie/compression.py
aigie/config.py
aigie/context.py
aigie/context_manager.py
aigie/cost_tracking.py
aigie/datasets.py
aigie/decorators.py
aigie/decorators_v2.py
aigie/decorators_v3.py
aigie/evaluation.py
aigie/evaluations.py
aigie/exceptions.py
aigie/experiments.py
aigie/feedback.py
aigie/graph_view.py
aigie/health.py
aigie/judges.py
aigie/langgraph.py
aigie/leaderboards.py
aigie/learning.py
aigie/licensing.py
aigie/mode_controller.py
aigie/observe.py
aigie/opentelemetry.py
aigie/playground.py
aigie/prompts.py
aigie/py.typed
aigie/pytest_plugin.py
aigie/query_api.py
aigie/recommendations.py
aigie/remediation.py
aigie/result.py
aigie/run_context.py
aigie/safety_metrics.py
aigie/sampling.py
aigie/schemas.py
aigie/scrubber.py
aigie/sessions.py
aigie/signals.py
aigie/span.py
aigie/span_replay.py
aigie/streaming.py
aigie/summary_evaluators.py
aigie/sync_client.py
aigie/tools.py
aigie/trace.py
aigie/types.py
aigie/uuid7.py
aigie/workflows.py
aigie/wrappers.py
aigie/wrappers_bedrock.py
aigie/wrappers_cohere.py
aigie/agents/__init__.py
aigie/agents/execution_cycle.py
aigie/agents/goal_tracking.py
aigie/agents/loop_detection.py
aigie/auto_instrument/__init__.py
aigie/auto_instrument/dspy.py
aigie/auto_instrument/haystack.py
aigie/auto_instrument/langchain.py
aigie/auto_instrument/langgraph.py
aigie/auto_instrument/llm.py
aigie/auto_instrument/tools.py
aigie/auto_instrument/trace.py
aigie/callbacks/__init__.py
aigie/callbacks/base.py
aigie/callbacks/generic_webhook.py
aigie/drift/__init__.py
aigie/drift/monitor.py
aigie/evaluation/__init__.py
aigie/evaluation/llm_judge.py
aigie/evaluation/scorers.py
aigie/gateway/__init__.py
aigie/gateway/client.py
aigie/gateway/fallback.py
aigie/gateway/handlers.py
aigie/gateway/middleware.py
aigie/gateway/validation.py
aigie-0.2.9.dist-info/METADATA
aigie-0.2.9.dist-info/WHEEL
aigie-0.2.9.dist-info/entry_points.txt
aigie-0.2.9.dist-info/top_level.txt
aigie-0.2.9.dist-info/RECORD
