Metadata-Version: 2.4
Name: aigie
Version: 0.2.9
Summary: Enterprise-grade AI agent reliability monitoring and autonomous remediation
Home-page: https://github.com/aigie/aigie-sdk
Author: Aigie Team
Author-email: support@aigie.io
Project-URL: Documentation, https://docs.aigie.io
Project-URL: Source, https://github.com/aigie/aigie-sdk
Project-URL: Tracker, https://github.com/aigie/aigie-sdk/issues
Project-URL: Changelog, https://github.com/aigie/aigie-sdk/blob/main/CHANGELOG.md
Keywords: ai agent monitoring observability llm reliability remediation
Classifier: Development Status :: 4 - Beta
Classifier: Intended Audience :: Developers
Classifier: License :: OSI Approved :: MIT License
Classifier: Programming Language :: Python :: 3
Classifier: Programming Language :: Python :: 3.9
Classifier: Programming Language :: Python :: 3.10
Classifier: Programming Language :: Python :: 3.11
Classifier: Programming Language :: Python :: 3.12
Classifier: Topic :: Software Development :: Libraries :: Python Modules
Classifier: Topic :: Scientific/Engineering :: Artificial Intelligence
Requires-Python: >=3.9
Requires-Dist: httpx>=0.25.0
Provides-Extra: compression
Requires-Dist: zstandard>=0.22.0; extra == "compression"
Provides-Extra: openai
Requires-Dist: openai>=1.0.0; extra == "openai"
Provides-Extra: anthropic
Requires-Dist: anthropic>=0.18.0; extra == "anthropic"
Provides-Extra: gemini
Requires-Dist: google-generativeai>=0.3.0; extra == "gemini"
Provides-Extra: langchain
Requires-Dist: langchain-core>=0.1.0; extra == "langchain"
Provides-Extra: langgraph
Requires-Dist: langgraph>=0.0.20; extra == "langgraph"
Requires-Dist: langchain-core>=0.1.0; extra == "langgraph"
Provides-Extra: browser-use
Requires-Dist: browser-use>=0.1.0; extra == "browser-use"
Requires-Dist: Pillow>=10.0.0; extra == "browser-use"
Provides-Extra: crewai
Requires-Dist: crewai>=0.28.0; extra == "crewai"
Provides-Extra: autogen
Requires-Dist: pyautogen>=0.2.0; extra == "autogen"
Provides-Extra: llamaindex
Requires-Dist: llama-index>=0.10.0; extra == "llamaindex"
Provides-Extra: openai-agents
Requires-Dist: openai-agents>=0.0.3; extra == "openai-agents"
Provides-Extra: dspy
Requires-Dist: dspy-ai>=2.4.0; extra == "dspy"
Provides-Extra: claude-agent-sdk
Requires-Dist: claude-agent-sdk>=0.0.10; extra == "claude-agent-sdk"
Provides-Extra: strands
Requires-Dist: strands-agents>=0.1.0; extra == "strands"
Provides-Extra: google-adk
Requires-Dist: google-adk>=1.0.0; extra == "google-adk"
Provides-Extra: instructor
Requires-Dist: instructor>=1.0.0; extra == "instructor"
Provides-Extra: semantic-kernel
Requires-Dist: semantic-kernel>=1.0.0; extra == "semantic-kernel"
Provides-Extra: pinecone
Requires-Dist: pinecone-client>=3.0.0; extra == "pinecone"
Provides-Extra: qdrant
Requires-Dist: qdrant-client>=1.7.0; extra == "qdrant"
Provides-Extra: chromadb
Requires-Dist: chromadb>=0.4.0; extra == "chromadb"
Provides-Extra: weaviate
Requires-Dist: weaviate-client>=4.0.0; extra == "weaviate"
Provides-Extra: vectordbs
Requires-Dist: pinecone-client>=3.0.0; extra == "vectordbs"
Requires-Dist: qdrant-client>=1.7.0; extra == "vectordbs"
Requires-Dist: chromadb>=0.4.0; extra == "vectordbs"
Requires-Dist: weaviate-client>=4.0.0; extra == "vectordbs"
Provides-Extra: opentelemetry
Requires-Dist: opentelemetry-api>=1.20.0; extra == "opentelemetry"
Requires-Dist: opentelemetry-sdk>=1.20.0; extra == "opentelemetry"
Provides-Extra: pandas
Requires-Dist: pandas>=1.5.0; extra == "pandas"
Provides-Extra: dev
Requires-Dist: pytest>=7.4.0; extra == "dev"
Requires-Dist: pytest-asyncio>=0.21.0; extra == "dev"
Requires-Dist: pytest-cov>=4.1.0; extra == "dev"
Requires-Dist: pytest-httpx>=0.30.0; extra == "dev"
Requires-Dist: pytest-benchmark>=4.0.0; extra == "dev"
Requires-Dist: pytest-mock>=3.12.0; extra == "dev"
Requires-Dist: respx>=0.20.0; extra == "dev"
Requires-Dist: black>=23.0.0; extra == "dev"
Requires-Dist: isort>=5.12.0; extra == "dev"
Requires-Dist: mypy>=1.5.0; extra == "dev"
Requires-Dist: ruff>=0.1.0; extra == "dev"
Provides-Extra: docs
Requires-Dist: sphinx>=7.0.0; extra == "docs"
Requires-Dist: sphinx-rtd-theme>=1.3.0; extra == "docs"
Requires-Dist: sphinx-autodoc-typehints>=1.24.0; extra == "docs"
Provides-Extra: all
Requires-Dist: zstandard>=0.22.0; extra == "all"
Requires-Dist: openai>=1.0.0; extra == "all"
Requires-Dist: anthropic>=0.18.0; extra == "all"
Requires-Dist: google-generativeai>=0.3.0; extra == "all"
Requires-Dist: langchain-core>=0.1.0; extra == "all"
Requires-Dist: langgraph>=0.0.20; extra == "all"
Requires-Dist: browser-use>=0.1.0; extra == "all"
Requires-Dist: Pillow>=10.0.0; extra == "all"
Requires-Dist: crewai>=0.28.0; extra == "all"
Requires-Dist: pyautogen>=0.2.0; extra == "all"
Requires-Dist: llama-index>=0.10.0; extra == "all"
Requires-Dist: openai-agents>=0.0.3; extra == "all"
Requires-Dist: dspy-ai>=2.4.0; extra == "all"
Requires-Dist: claude-agent-sdk>=0.0.10; extra == "all"
Requires-Dist: strands-agents>=0.1.0; extra == "all"
Requires-Dist: google-adk>=1.0.0; extra == "all"
Requires-Dist: instructor>=1.0.0; extra == "all"
Requires-Dist: semantic-kernel>=1.0.0; extra == "all"
Requires-Dist: opentelemetry-api>=1.20.0; extra == "all"
Requires-Dist: opentelemetry-sdk>=1.20.0; extra == "all"
Provides-Extra: integrations
Requires-Dist: langchain-core>=0.1.0; extra == "integrations"
Requires-Dist: langgraph>=0.0.20; extra == "integrations"
Requires-Dist: browser-use>=0.1.0; extra == "integrations"
Requires-Dist: Pillow>=10.0.0; extra == "integrations"
Requires-Dist: crewai>=0.28.0; extra == "integrations"
Requires-Dist: pyautogen>=0.2.0; extra == "integrations"
Requires-Dist: llama-index>=0.10.0; extra == "integrations"
Requires-Dist: openai-agents>=0.0.3; extra == "integrations"
Requires-Dist: dspy-ai>=2.4.0; extra == "integrations"
Requires-Dist: claude-agent-sdk>=0.0.10; extra == "integrations"
Requires-Dist: strands-agents>=0.1.0; extra == "integrations"
Requires-Dist: google-adk>=1.0.0; extra == "integrations"
Requires-Dist: instructor>=1.0.0; extra == "integrations"
Requires-Dist: semantic-kernel>=1.0.0; extra == "integrations"
Dynamic: author
Dynamic: author-email
Dynamic: classifier
Dynamic: description
Dynamic: description-content-type
Dynamic: home-page
Dynamic: keywords
Dynamic: project-url
Dynamic: provides-extra
Dynamic: requires-dist
Dynamic: requires-python
Dynamic: summary
